youtube_search_sdk/__init__.py
youtube_search_sdk/client.py
youtube_search_sdk-0.1.0.dist-info/METADATA
youtube_search_sdk-0.1.0.dist-info/WHEEL
youtube_search_sdk-0.1.0.dist-info/licenses/LICENSE
youtube_search_sdk-0.1.0.dist-info/RECORD
