Metadata-Version: 2.4
Name: youtube_search_sdk
Version: 0.1.0
Summary: SDK for interacting with YouTube Search API
Project-URL: Homepage, https://github.com/yourusername/youtube_search_sdk
Project-URL: Bug Tracker, https://github.com/yourusername/youtube_search_sdk/issues
Author-email: Your Name <your.email@example.com>
License-File: LICENSE
Classifier: Development Status :: 4 - Beta
Classifier: Intended Audience :: Developers
Classifier: License :: OSI Approved :: MIT License
Classifier: Operating System :: OS Independent
Classifier: Programming Language :: Python :: 3
Classifier: Topic :: Software Development :: Libraries :: Python Modules
Requires-Python: >=3.8
Requires-Dist: httpx>=0.24.0
Requires-Dist: pydantic>=2.0.0
Provides-Extra: dev
Requires-Dist: black>=21.0; extra == 'dev'
Requires-Dist: isort>=5.0; extra == 'dev'
Requires-Dist: mypy>=1.0.0; extra == 'dev'
Requires-Dist: pytest>=6.0; extra == 'dev'
Requires-Dist: requests>=2.31.0; extra == 'dev'
